dictionary/__init__.py
dictionary/dictionary.py
aleyna_sutbas_cs453_hw1-2.0.0.dist-info/METADATA
aleyna_sutbas_cs453_hw1-2.0.0.dist-info/WHEEL
aleyna_sutbas_cs453_hw1-2.0.0.dist-info/top_level.txt
aleyna_sutbas_cs453_hw1-2.0.0.dist-info/RECORD
